[
	{ "dec": 9, "char": "", "desc": "tab" },
	{ "dec": 10, "char": "", "desc": "newline" },
	{ "dec": 13, "char": "", "desc": "prefix for newline on windows" },

	{ "dec": 32, "char": " ", "desc": "space" },
	{ "dec": 33, "char": "!", "desc": "exclamation mark" },
	{ "dec": 34, "char": "\"", "desc": "double quote" },
	{ "dec": 35, "char": "#", "desc": "hash" },
	{ "dec": 36, "char": "$", "desc": "dollar sign" },
	{ "dec": 37, "char": "%", "desc": "percent sign" },
	{ "dec": 38, "char": "&", "desc": "ampersand" },
	{ "dec": 39, "char": "'", "desc": "apostrophe / single quote" },
	{ "dec": 40, "char": "(", "desc": "left bracket" },
	{ "dec": 41, "char": ")", "desc": "right bracket" },
	{ "dec": 42, "char": "*", "desc": "asterisk" },
	{ "dec": 43, "char": "+", "desc": "plus" },
	{ "dec": 44, "char": ",", "desc": "comma" },
	{ "dec": 45, "char": "-", "desc": "hyphen" },
	{ "dec": 46, "char": ".", "desc": "period" },
	{ "dec": 47, "char": "/", "desc": "forward slash" },
	{ "dec": 48, "char": "0", "desc": "digit zero" },
	{ "dec": 49, "char": "1", "desc": "digit one" },
	{ "dec": 50, "char": "2", "desc": "digit two" },
	{ "dec": 51, "char": "3", "desc": "digit three" },
	{ "dec": 52, "char": "4", "desc": "digit four" },
	{ "dec": 53, "char": "5", "desc": "digit five" },
	{ "dec": 54, "char": "6", "desc": "digit six" },
	{ "dec": 55, "char": "7", "desc": "digit seven" },
	{ "dec": 56, "char": "8", "desc": "digit eight" },
	{ "dec": 57, "char": "9", "desc": "digit nine" },
	{ "dec": 58, "char": ":", "desc": "colon" },
	{ "dec": 59, "char": ";", "desc": "semicolon" },
	{ "dec": 60, "char": "<", "desc": "less than sign" },
	{ "dec": 61, "char": "=", "desc": "equals sign" },
	{ "dec": 62, "char": ">", "desc": "greater than sign" },
	{ "dec": 63, "char": "?", "desc": "question mark" },
	{ "dec": 64, "char": "@", "desc": "at sign" },

	{ "dec": 65, "char": "A", "desc": "uppercase A" },
	{ "dec": 66, "char": "B", "desc": "uppercase B" },
	{ "dec": 67, "char": "C", "desc": "uppercase C" },
	{ "dec": 68, "char": "D", "desc": "uppercase D" },
	{ "dec": 69, "char": "E", "desc": "uppercase E" },
	{ "dec": 70, "char": "F", "desc": "uppercase F" },
	{ "dec": 71, "char": "G", "desc": "uppercase G" },
	{ "dec": 72, "char": "H", "desc": "uppercase H" },
	{ "dec": 73, "char": "I", "desc": "uppercase I" },
	{ "dec": 74, "char": "J", "desc": "uppercase J" },
	{ "dec": 75, "char": "K", "desc": "uppercase K" },
	{ "dec": 76, "char": "L", "desc": "uppercase L" },
	{ "dec": 77, "char": "M", "desc": "uppercase M" },
	{ "dec": 78, "char": "N", "desc": "uppercase N" },
	{ "dec": 79, "char": "O", "desc": "uppercase O" },
	{ "dec": 80, "char": "P", "desc": "uppercase P" },
	{ "dec": 81, "char": "Q", "desc": "uppercase Q" },
	{ "dec": 82, "char": "R", "desc": "uppercase R" },
	{ "dec": 83, "char": "S", "desc": "uppercase S" },
	{ "dec": 84, "char": "T", "desc": "uppercase T" },
	{ "dec": 85, "char": "U", "desc": "uppercase U" },
	{ "dec": 86, "char": "V", "desc": "uppercase V" },
	{ "dec": 87, "char": "W", "desc": "uppercase W" },
	{ "dec": 88, "char": "X", "desc": "uppercase X" },
	{ "dec": 89, "char": "Y", "desc": "uppercase Y" },
	{ "dec": 90, "char": "Z", "desc": "uppercase Z" },

	{ "dec": 91, "char": "[", "desc": "left square bracket" },
	{ "dec": 92, "char": "\\", "desc": "backslash" },
	{ "dec": 93, "char": "]", "desc": "right square bracket" },
	{ "dec": 94, "char": "^", "desc": "caret" },
	{ "dec": 95, "char": "_", "desc": "underscore" },
	{ "dec": 96, "char": "`", "desc": "backtick" },

	{ "dec": 97, "char": "a", "desc": "lowercase a" },
	{ "dec": 98, "char": "b", "desc": "lowercase b" },
	{ "dec": 99, "char": "c", "desc": "lowercase c" },
	{ "dec": 100, "char": "d", "desc": "lowercase d" },
	{ "dec": 101, "char": "e", "desc": "lowercase e" },
	{ "dec": 102, "char": "f", "desc": "lowercase f" },
	{ "dec": 103, "char": "g", "desc": "lowercase g" },
	{ "dec": 104, "char": "h", "desc": "lowercase h" },
	{ "dec": 105, "char": "i", "desc": "lowercase i" },
	{ "dec": 106, "char": "j", "desc": "lowercase j" },
	{ "dec": 107, "char": "k", "desc": "lowercase k" },
	{ "dec": 108, "char": "l", "desc": "lowercase l" },
	{ "dec": 109, "char": "m", "desc": "lowercase m" },
	{ "dec": 110, "char": "n", "desc": "lowercase n" },
	{ "dec": 111, "char": "o", "desc": "lowercase o" },
	{ "dec": 112, "char": "p", "desc": "lowercase p" },
	{ "dec": 113, "char": "q", "desc": "lowercase q" },
	{ "dec": 114, "char": "r", "desc": "lowercase r" },
	{ "dec": 115, "char": "s", "desc": "lowercase s" },
	{ "dec": 116, "char": "t", "desc": "lowercase t" },
	{ "dec": 117, "char": "u", "desc": "lowercase u" },
	{ "dec": 118, "char": "v", "desc": "lowercase v" },
	{ "dec": 119, "char": "w", "desc": "lowercase w" },
	{ "dec": 120, "char": "x", "desc": "lowercase x" },
	{ "dec": 121, "char": "y", "desc": "lowercase y" },
	{ "dec": 122, "char": "z", "desc": "lowercase z" },

	{ "dec": 123, "char": "{", "desc": "left curly brace" },
	{ "dec": 124, "char": "|", "desc": "vertical bar" },
	{ "dec": 125, "char": "}", "desc": "right curly brace" },
	{ "dec": 126, "char": "~", "desc": "tilde" }
]
